COPYING
MANIFEST.in
README
health_disability_view.xml
setup.py
./__init__.py
./health_disability.py
./health_disability_view.xml
./tryton.cfg
./data/activity_and_participation.xml
./data/body_functions.xml
./data/body_structures.xml
./data/categories.xml
./data/environmental_factors.xml
./doc/index.rst
./locale/ar.po
./locale/de.po
./locale/el.po
./locale/es.po
./locale/fr.po
./locale/it_IT.po
./locale/ja_JP.po
./locale/lo.po
./locale/pt_BR.po
./locale/zh_CN.po
./tests/__init__.py
./tests/test_health_disability.py
./view/gnuhealth_activity_and_participation_assessment_form.xml
./view/gnuhealth_activity_and_participation_assessment_tree.xml
./view/gnuhealth_activity_and_participation_form.xml
./view/gnuhealth_activity_and_participation_tree.xml
./view/gnuhealth_body_function_assessment_form.xml
./view/gnuhealth_body_function_assessment_tree.xml
./view/gnuhealth_body_function_form.xml
./view/gnuhealth_body_function_tree.xml
./view/gnuhealth_body_structure_assessment_form.xml
./view/gnuhealth_body_structure_assessment_tree.xml
./view/gnuhealth_body_structure_form.xml
./view/gnuhealth_body_structure_tree.xml
./view/gnuhealth_environmental_factor_assessment_form.xml
./view/gnuhealth_environmental_factor_assessment_tree.xml
./view/gnuhealth_environmental_factor_form.xml
./view/gnuhealth_environmental_factor_tree.xml
./view/gnuhealth_patient_amputation_form.xml
./view/gnuhealth_patient_amputation_tree.xml
./view/gnuhealth_patient_disability_assessment_form.xml
./view/gnuhealth_patient_disability_assessment_tree.xml
./view/gnuhealth_patient_form.xml
./view/gnuhealth_patient_prothesis_form.xml
./view/gnuhealth_patient_prothesis_tree.xml
./view/gnuhealth_product_form.xml
data/activity_and_participation.xml
data/body_functions.xml
data/body_structures.xml
data/categories.xml
data/environmental_factors.xml
locale/ar.po
locale/de.po
locale/el.po
locale/es.po
locale/fr.po
locale/it_IT.po
locale/ja_JP.po
locale/lo.po
locale/pt_BR.po
locale/zh_CN.po
trytond_health_disability.egg-info/PKG-INFO
trytond_health_disability.egg-info/SOURCES.txt
trytond_health_disability.egg-info/dependency_links.txt
trytond_health_disability.egg-info/entry_points.txt
trytond_health_disability.egg-info/not-zip-safe
trytond_health_disability.egg-info/requires.txt
trytond_health_disability.egg-info/top_level.txt
